geyser/__init__.py
geyser/assets/bpool.abi
geyser/assets/erc20.abi
geyser/assets/unipool.abi
geyser/cli.py
geyser/dexs/balancer.py
geyser/dexs/dex.py
geyser/dexs/uni_like.py
geyser/types.py
geyser/utils.py
geyser/vault.py
geyser_cli-0.1.0.dist-info/entry_points.txt
geyser_cli-0.1.0.dist-info/LICENSE
geyser_cli-0.1.0.dist-info/WHEEL
geyser_cli-0.1.0.dist-info/METADATA
geyser_cli-0.1.0.dist-info/RECORD
