Metadata-Version: 2.1
Name: geyser-cli
Version: 0.1.0
Summary: A command line utility for the Ampleforth Geyser v2
License: MIT
Author: pascal-merkleplant
Author-email: pascal@merkleplant.xyz
Requires-Python: >=3.9,<4.0
Classifier: License :: OSI Approved :: MIT License
Classifier: Programming Language :: Python :: 3
Classifier: Programming Language :: Python :: 3.9
Requires-Dist: click (>=8.0.1,<9.0.0)
Requires-Dist: tabulate (>=0.8.9,<0.9.0)
Requires-Dist: web3 (>=5.21.0,<6.0.0)
